<?xml version="1.0" encoding="UTF-8"?><record_update table="sp_instance">
    <sp_instance action="DELETE">
        <active>true</active>
        <class_name/>
        <color>primary</color>
        <css/>
        <glyph/>
        <id/>
        <order>1</order>
        <roles/>
        <short_description/>
        <size>md</size>
        <sp_column display_value="3">df92bc72973f3590601fb998c253af72</sp_column>
        <sp_widget display_value="link-button">abc50de6d702120023c84f80de61036a</sp_widget>
        <sys_class_name>sp_instance</sys_class_name>
        <sys_created_by>admin</sys_created_by>
        <sys_created_on>2024-01-21 10:58:15</sys_created_on>
        <sys_id>4a03747e97fb3590601fb998c253aff7</sys_id>
        <sys_mod_count>1</sys_mod_count>
        <sys_name/>
        <sys_package display_value="Technical Assistance Management" source="x_982322_technic_2">0dfe49e69733f190601fb998c253af18</sys_package>
        <sys_policy/>
        <sys_scope display_value="Technical Assistance Management">0dfe49e69733f190601fb998c253af18</sys_scope>
        <sys_update_name>sp_instance_4a03747e97fb3590601fb998c253aff7</sys_update_name>
        <sys_updated_by>admin</sys_updated_by>
        <sys_updated_on>2024-01-21 10:58:57</sys_updated_on>
        <title/>
        <url/>
        <widget_parameters><![CDATA[{
	"href": {
		"value": "",
		"displayValue": ""
	},
	"button_text": {
		"value": "",
		"displayValue": ""
	}
}]]></widget_parameters>
    </sp_instance>
    <sys_translated_text action="DELETE" query="documentkey=4a03747e97fb3590601fb998c253aff7"/>
    <sys_update_version action="INSERT_OR_UPDATE">
        <action>DELETE</action>
        <application display_value="Technical Assistance Management">0dfe49e69733f190601fb998c253af18</application>
        <file_path/>
        <instance_id>d1e11c19db47ddd042b321c4059619fe</instance_id>
        <instance_name>dev143293</instance_name>
        <name>sp_instance_4a03747e97fb3590601fb998c253aff7</name>
        <payload>&lt;?xml version="1.0" encoding="UTF-8"?&gt;&lt;record_update table="sp_instance"&gt;&lt;sp_instance action="INSERT_OR_UPDATE"&gt;&lt;active&gt;true&lt;/active&gt;&lt;class_name/&gt;&lt;color&gt;primary&lt;/color&gt;&lt;css/&gt;&lt;glyph/&gt;&lt;id/&gt;&lt;order&gt;1&lt;/order&gt;&lt;roles/&gt;&lt;short_description/&gt;&lt;size&gt;md&lt;/size&gt;&lt;sp_column display_value="3"&gt;df92bc72973f3590601fb998c253af72&lt;/sp_column&gt;&lt;sp_widget display_value="link-button"&gt;abc50de6d702120023c84f80de61036a&lt;/sp_widget&gt;&lt;sys_class_name&gt;sp_instance&lt;/sys_class_name&gt;&lt;sys_created_by&gt;admin&lt;/sys_created_by&gt;&lt;sys_created_on&gt;2024-01-21 10:58:15&lt;/sys_created_on&gt;&lt;sys_id&gt;4a03747e97fb3590601fb998c253aff7&lt;/sys_id&gt;&lt;sys_mod_count&gt;1&lt;/sys_mod_count&gt;&lt;sys_name/&gt;&lt;sys_package display_value="Technical Assistance Management" source="x_982322_technic_2"&gt;0dfe49e69733f190601fb998c253af18&lt;/sys_package&gt;&lt;sys_policy/&gt;&lt;sys_scope display_value="Technical Assistance Management"&gt;0dfe49e69733f190601fb998c253af18&lt;/sys_scope&gt;&lt;sys_update_name&gt;sp_instance_4a03747e97fb3590601fb998c253aff7&lt;/sys_update_name&gt;&lt;sys_updated_by&gt;admin&lt;/sys_updated_by&gt;&lt;sys_updated_on&gt;2024-01-21 10:58:57&lt;/sys_updated_on&gt;&lt;title/&gt;&lt;url/&gt;&lt;widget_parameters&gt;&lt;![CDATA[{
	"href": {
		"value": "",
		"displayValue": ""
	},
	"button_text": {
		"value": "",
		"displayValue": ""
	}
}]]&gt;&lt;/widget_parameters&gt;&lt;/sp_instance&gt;&lt;sys_translated_text action="delete_multiple" query="documentkey=4a03747e97fb3590601fb998c253aff7"/&gt;&lt;/record_update&gt;</payload>
        <payload_hash>-690712699</payload_hash>
        <record_name/>
        <reverted_from/>
        <source>89fe49e69733f190601fb998c253af1d</source>
        <source_table>sys_update_set</source_table>
        <state>previous</state>
        <sys_created_by>admin</sys_created_by>
        <sys_created_on>2024-01-21 10:58:58</sys_created_on>
        <sys_id>ac33f47e97fb3590601fb998c253afe8</sys_id>
        <sys_mod_count>0</sys_mod_count>
        <sys_recorded_at>18d2bac72940000001</sys_recorded_at>
        <sys_updated_by>admin</sys_updated_by>
        <sys_updated_on>2024-01-21 10:58:58</sys_updated_on>
        <type>Instance</type>
        <update_guid>2433f47e1cfb3590f1a9b0e9e3d16be8</update_guid>
        <update_guid_history>2433f47e1cfb3590f1a9b0e9e3d16be8:-690712699,4e03747e0ffb3590f0bd970f70a2c0f8:2078694256</update_guid_history>
    </sys_update_version>
    <sys_metadata_delete action="INSERT_OR_UPDATE">
        <sys_audit_delete display_value="">fe37f836973f3590601fb998c253aff9</sys_audit_delete>
        <sys_class_name>sys_metadata_delete</sys_class_name>
        <sys_created_by>admin</sys_created_by>
        <sys_created_on>2024-01-21 11:16:35</sys_created_on>
        <sys_db_object display_value="" name="sp_instance">sp_instance</sys_db_object>
        <sys_id>16dfe43e80f14798a69ed48a9d351710</sys_id>
        <sys_metadata>4a03747e97fb3590601fb998c253aff7</sys_metadata>
        <sys_mod_count>0</sys_mod_count>
        <sys_name/>
        <sys_package display_value="Technical Assistance Management" source="x_982322_technic_2">0dfe49e69733f190601fb998c253af18</sys_package>
        <sys_parent/>
        <sys_policy/>
        <sys_scope display_value="Technical Assistance Management">0dfe49e69733f190601fb998c253af18</sys_scope>
        <sys_scope_delete display_value="">e13ddd0218004bf182994ad8914299a9</sys_scope_delete>
        <sys_update_name>sp_instance_4a03747e97fb3590601fb998c253aff7</sys_update_name>
        <sys_update_version display_value="sp_instance_4a03747e97fb3590601fb998c253aff7">ac33f47e97fb3590601fb998c253afe8</sys_update_version>
        <sys_updated_by>admin</sys_updated_by>
        <sys_updated_on>2024-01-21 11:16:35</sys_updated_on>
    </sys_metadata_delete>
</record_update>
